salesforce_bulk/__init__.py
salesforce_bulk/__version__.py
salesforce_bulk/bulk_states.py
salesforce_bulk/csv_adapter.py
salesforce_bulk/salesforce_bulk.py
salesforce_bulk/util.py
salesforce_bulk-2.1.0.dist-info/DESCRIPTION.rst
salesforce_bulk-2.1.0.dist-info/METADATA
salesforce_bulk-2.1.0.dist-info/RECORD
salesforce_bulk-2.1.0.dist-info/WHEEL
salesforce_bulk-2.1.0.dist-info/metadata.json
salesforce_bulk-2.1.0.dist-info/top_level.txt
