Metadata-Version: 1.1
Name: salesforce-bulk
Version: 2.1.0
Summary: Python interface to the Salesforce.com Bulk API.
Home-page: https://github.com/heroku/salesforce-bulk
Author: Scott Persinger
Author-email: scottp@heroku.com
License: MIT
Platform: UNKNOWN
Classifier: Development Status :: 5 - Production/Stable
Classifier: Intended Audience :: Developers
Classifier: Natural Language :: English
Classifier: License :: OSI Approved :: MIT License
Classifier: Programming Language :: Python
Classifier: Programming Language :: Python :: 2.7
Classifier: Programming Language :: Python :: 3.3
Classifier: Programming Language :: Python :: 3.4
Classifier: Programming Language :: Python :: 3.5
Classifier: Programming Language :: Python :: 3.6
